odoo/addons/hr_recruitment_phone/README.rst
odoo/addons/hr_recruitment_phone/__init__.py
odoo/addons/hr_recruitment_phone/__manifest__.py
odoo/addons/hr_recruitment_phone/i18n/es.po
odoo/addons/hr_recruitment_phone/i18n/hr_recruitment_phone.pot
odoo/addons/hr_recruitment_phone/i18n/it.po
odoo/addons/hr_recruitment_phone/i18n/tr.po
odoo/addons/hr_recruitment_phone/models/__init__.py
odoo/addons/hr_recruitment_phone/models/hr_applicant.py
odoo/addons/hr_recruitment_phone/readme/CONTRIBUTORS.rst
odoo/addons/hr_recruitment_phone/readme/DESCRIPTION.rst
odoo/addons/hr_recruitment_phone/security/ir.model.access.csv
odoo/addons/hr_recruitment_phone/static/description/icon.png
odoo/addons/hr_recruitment_phone/static/description/index.html
odoo/addons/hr_recruitment_phone/tests/__init__.py
odoo/addons/hr_recruitment_phone/tests/test_phone.py
odoo14_addon_hr_recruitment_phone-14.0.1.0.1.dev11.dist-info/METADATA
odoo14_addon_hr_recruitment_phone-14.0.1.0.1.dev11.dist-info/WHEEL
odoo14_addon_hr_recruitment_phone-14.0.1.0.1.dev11.dist-info/top_level.txt
odoo14_addon_hr_recruitment_phone-14.0.1.0.1.dev11.dist-info/RECORD
